selo_linku/__init__.py
selo_linku/_apiv1.py
selo_linku-0.0.1.dist-info/METADATA
selo_linku-0.0.1.dist-info/WHEEL
selo_linku-0.0.1.dist-info/licenses/LICENSE
selo_linku-0.0.1.dist-info/RECORD
