Metadata-Version: 2.3
Name: selo_linku
Version: 0.0.1
Summary: Python library for interacting with sona Linku (the lipu Linku API)
Project-URL: Homepage, https://github.com/Belu-cat/seloLinkuPason
Project-URL: Issues, https://github.com/Belu-cat/seloLinkuPason/issues
Author-email: Thecoolcats <thecoolcats75@gmail.com>
License-File: LICENSE
Classifier: License :: OSI Approved :: MIT License
Classifier: Operating System :: OS Independent
Classifier: Programming Language :: Python :: 3
Requires-Python: >=3.12
